akeyless_cdktf/__init__.py
akeyless_cdktf/_jsii/__init__.py
akeyless_cdktf/_jsii/akeyless@0.0.0.jsii.tgz
akeyless_cdktf/associate_role_auth_method/__init__.py
akeyless_cdktf/auth_method/__init__.py
akeyless_cdktf/auth_method_api_key/__init__.py
akeyless_cdktf/auth_method_aws_iam/__init__.py
akeyless_cdktf/auth_method_azure_ad/__init__.py
akeyless_cdktf/auth_method_cert/__init__.py
akeyless_cdktf/auth_method_gcp/__init__.py
akeyless_cdktf/auth_method_k8_s/__init__.py
akeyless_cdktf/auth_method_ldap/__init__.py
akeyless_cdktf/auth_method_oauth2/__init__.py
akeyless_cdktf/auth_method_oidc/__init__.py
akeyless_cdktf/auth_method_saml/__init__.py
akeyless_cdktf/auth_method_universal_identity/__init__.py
akeyless_cdktf/certificate/__init__.py
akeyless_cdktf/classic_key/__init__.py
akeyless_cdktf/data_akeyless_auth/__init__.py
akeyless_cdktf/data_akeyless_auth_method/__init__.py
akeyless_cdktf/data_akeyless_certificate/__init__.py
akeyless_cdktf/data_akeyless_csr/__init__.py
akeyless_cdktf/data_akeyless_detokenize/__init__.py
akeyless_cdktf/data_akeyless_dynamic_secret/__init__.py
akeyless_cdktf/data_akeyless_k8_s_auth_config/__init__.py
akeyless_cdktf/data_akeyless_kube_exec_creds/__init__.py
akeyless_cdktf/data_akeyless_pki_certificate/__init__.py
akeyless_cdktf/data_akeyless_producer_tmp_creds/__init__.py
akeyless_cdktf/data_akeyless_reset_access_key/__init__.py
akeyless_cdktf/data_akeyless_role/__init__.py
akeyless_cdktf/data_akeyless_rotated_secret/__init__.py
akeyless_cdktf/data_akeyless_rsa_pub/__init__.py
akeyless_cdktf/data_akeyless_secret/__init__.py
akeyless_cdktf/data_akeyless_ssh_certificate/__init__.py
akeyless_cdktf/data_akeyless_static_secret/__init__.py
akeyless_cdktf/data_akeyless_tags/__init__.py
akeyless_cdktf/data_akeyless_target/__init__.py
akeyless_cdktf/data_akeyless_target_details/__init__.py
akeyless_cdktf/data_akeyless_tokenize/__init__.py
akeyless_cdktf/dfc_key/__init__.py
akeyless_cdktf/dynamic_secret_artifactory/__init__.py
akeyless_cdktf-1.11.4.dist-info/METADATA
akeyless_cdktf-1.11.4.dist-info/WHEEL
akeyless_cdktf-1.11.4.dist-info/RECORD
