Metadata-Version: 2.1
Name: akeyless-cdktf
Version: 1.11.4
Summary: CDKTF for Akeyless
Author: Akeyless
Requires-Python: >=3.12,<4.0
Classifier: Programming Language :: Python :: 3
Requires-Dist: cdktf (>=0.20.7,<0.21.0)
